common/__init__.py
common/config.py
common/config_ops.py
common/embedding_types.py
common/generate_config.py
common/model.py
common/train.py
common/train_mgpu.py
common/transform.py
common/utils.py
deep_text-1.3.7.dist-info/DESCRIPTION.rst
deep_text-1.3.7.dist-info/METADATA
deep_text-1.3.7.dist-info/RECORD
deep_text-1.3.7.dist-info/WHEEL
deep_text-1.3.7.dist-info/entry_points.txt
deep_text-1.3.7.dist-info/metadata.json
deep_text-1.3.7.dist-info/top_level.txt
deepcls/__init__.py
deepcls/config.py
deepcls/deepcls_eval.py
deepcls/default_custom.py
deepcls/main.py
deepcls/model.py
deepcls/textcnn.py
deepcls/textrnn.py
deepcls/train.py
deepcls/transform.py
deepcrf/__init__.py
deepcrf/config.py
deepcrf/default_custom.py
deepcrf/main.py
deepcrf/model.py
deepcrf/train.py
deepcrf/transform.py
deepemb/__init__.py
deepemb/config.py
deepemb/default_custom.py
deepemb/main.py
deepemb/model.py
deepemb/skip_thought.py
deepemb/train.py
deepemb/transform.py
deeplm/__init__.py
deeplm/config.py
deeplm/default_custom.py
deeplm/main.py
deeplm/model.py
deeplm/train.py
deeplm/transform.py
deepmatch/__init__.py
deepmatch/cdssm.py
deepmatch/config.py
deepmatch/default_custom.py
deepmatch/main.py
deepmatch/model.py
deepmatch/train.py
deepmatch/transform.py
deepocr/__init__.py
deepocr/cnn_lstm_ctc.py
deepocr/config.py
deepocr/default_custom.py
deepocr/main.py
deepocr/model.py
deepocr/train.py
deepocr/transform.py
