Metadata-Version: 2.0
Name: deep-text
Version: 1.3.7
Summary: Deep learning nlp model framework, provides command-line tools.
Home-page: https://gitee.com/wangsihong/deep-text
Author: wangsihong
Author-email: wangsihong@live.com
License: GPLv3
Keywords: deep-text,lstm-crf,crf,textrnn,textcnn,skip-thoughts,cdssm,ocr
Platform: any
Classifier: Development Status :: 4 - Beta
Classifier: Operating System :: OS Independent
Classifier: Intended Audience :: Developers
Classifier: License :: OSI Approved :: BSD License
Classifier: Programming Language :: Python
Classifier: Programming Language :: Python :: Implementation
Classifier: Programming Language :: Python :: 3
Classifier: Programming Language :: Python :: 3.6
Classifier: Topic :: Software Development :: Libraries
